GoYuyan101Fix1/README.md
GoYuyan101Fix1/__init__.py
GoYuyan101Fix1/__main__.py
GoYuyan101Fix1/file.epub
GoYuyan101Fix1/index.html
GoYuyan101Fix1/css/__init__.py
GoYuyan101Fix1/css/annotations.css
GoYuyan101Fix1/css/main.css
GoYuyan101Fix1/css/normalize.css
GoYuyan101Fix1/css/popup.css
GoYuyan101Fix1/font/__init__.py
GoYuyan101Fix1/font/fontello.eot
GoYuyan101Fix1/font/fontello.svg
GoYuyan101Fix1/font/fontello.ttf
GoYuyan101Fix1/font/fontello.woff
GoYuyan101Fix1/img/__init__.py
GoYuyan101Fix1/img/annotator-glyph-sprite.png
GoYuyan101Fix1/img/annotator-icon-sprite.png
GoYuyan101Fix1/img/apple-touch-icon.png
GoYuyan101Fix1/img/cancelfullscreen.png
GoYuyan101Fix1/img/close.png
GoYuyan101Fix1/img/fullscreen.png
GoYuyan101Fix1/img/loader.gif
GoYuyan101Fix1/img/menu-icon.png
GoYuyan101Fix1/img/save.png
GoYuyan101Fix1/img/saved.png
GoYuyan101Fix1/img/settings-s.png
GoYuyan101Fix1/img/settings.png
GoYuyan101Fix1/img/star.png
GoYuyan101Fix1/js/__init__.py
GoYuyan101Fix1/js/epub.js
GoYuyan101Fix1/js/epub.min.js
GoYuyan101Fix1/js/epub.min.map
GoYuyan101Fix1/js/hooks.min.js
GoYuyan101Fix1/js/hooks.min.map
GoYuyan101Fix1/js/reader.js
GoYuyan101Fix1/js/reader.js.map
GoYuyan101Fix1/js/reader.min.js
GoYuyan101Fix1/js/reader.min.map
GoYuyan101Fix1/js/hooks/__init__.py
GoYuyan101Fix1/js/hooks/extensions/__init__.py
GoYuyan101Fix1/js/hooks/extensions/highlight.js
GoYuyan101Fix1/js/libs/__init__.py
GoYuyan101Fix1/js/libs/jquery.min.js
GoYuyan101Fix1/js/libs/localforage.min.js
GoYuyan101Fix1/js/libs/screenfull.js
GoYuyan101Fix1/js/libs/screenfull.min.js
GoYuyan101Fix1/js/libs/zip.min.js
GoYuyan101Fix1/js/plugins/__init__.py
GoYuyan101Fix1/js/plugins/hypothesis.js
GoYuyan101Fix1/js/plugins/search.js
go_yuyan_101_fix1-2025.3.25.1.dist-info/METADATA
go_yuyan_101_fix1-2025.3.25.1.dist-info/WHEEL
go_yuyan_101_fix1-2025.3.25.1.dist-info/entry_points.txt
go_yuyan_101_fix1-2025.3.25.1.dist-info/top_level.txt
go_yuyan_101_fix1-2025.3.25.1.dist-info/RECORD
